passive_agent/__init__.py
passive_agent/cli.py
passive_agent/core.py
passive_agent_kahiroka-0.3.1.dist-info/METADATA
passive_agent_kahiroka-0.3.1.dist-info/WHEEL
passive_agent_kahiroka-0.3.1.dist-info/entry_points.txt
passive_agent_kahiroka-0.3.1.dist-info/licenses/LICENSE
passive_agent_kahiroka-0.3.1.dist-info/RECORD
