Metadata-Version: 2.4
Name: passive-agent-kahiroka
Version: 0.3.1
Summary: A passive agent for prompt engineering experiments with instruction-based context building
Project-URL: Homepage, https://github.com/kahiroka/passive-agent
Project-URL: Documentation, https://github.com/kahiroka/passive-agent#readme
Project-URL: Repository, https://github.com/kahiroka/passive-agent
Project-URL: Issues, https://github.com/kahiroka/passive-agent/issues
Author: kahiroka
License: MIT
License-File: LICENSE
Keywords: ai,context-building,llm,openai,openrouter,prompt-engineering
Classifier: Development Status :: 3 - Alpha
Classifier: Intended Audience :: Developers
Classifier: License :: OSI Approved :: MIT License
Classifier: Programming Language :: Python :: 3
Classifier: Programming Language :: Python :: 3.8
Classifier: Programming Language :: Python :: 3.9
Classifier: Programming Language :: Python :: 3.10
Classifier: Programming Language :: Python :: 3.11
Classifier: Programming Language :: Python :: 3.12
Classifier: Topic :: Scientific/Engineering :: Artificial Intelligence
Classifier: Topic :: Software Development :: Libraries :: Python Modules
Requires-Python: >=3.8
Requires-Dist: openai>=1.0.0
Provides-Extra: dev
Requires-Dist: black>=22.0; extra == 'dev'
Requires-Dist: pytest>=7.0; extra == 'dev'
Requires-Dist: ruff>=0.1.0; extra == 'dev'
